livingTree/IDConverter.py
livingTree/LineageTracker.py
livingTree/SuperTree.py
livingTree/TaxaRetriever.py
livingTree/TreeBuilder.py
livingTree/__init__.py
livingTree/utils.py
living_tree-0.0.6.dist-info/LICENSE
living_tree-0.0.6.dist-info/METADATA
living_tree-0.0.6.dist-info/WHEEL
living_tree-0.0.6.dist-info/top_level.txt
living_tree-0.0.6.dist-info/RECORD
