Metadata-Version: 2.1
Name: living-tree
Version: 0.0.6
Summary: An efficient toolkit for constructing and processing taxonomic trees (metagenomic reads count, remapping, etc.).
Home-page: https://github.com/AdeBC/living-tree-toolkit
Author: Hui Chong
Author-email: huichong.me@gmail.com
License: MIT
Keywords: taxonomic tree,living tree,tree data processing
Platform: UNKNOWN
Classifier: Development Status :: 5 - Production/Stable
Classifier: Intended Audience :: Science/Research
Classifier: Topic :: Scientific/Engineering :: Bio-Informatics
Classifier: Topic :: Scientific/Engineering :: Information Analysis
Classifier: Programming Language :: Python :: 3.7
Classifier: License :: OSI Approved :: MIT License
Classifier: Operating System :: OS Independent
License-File: LICENSE
Requires-Dist: ete3 (==3.1.1)
Requires-Dist: numpy (>=1.15.4)
Requires-Dist: pandas (>=0.23.4)
Requires-Dist: treelib (==1.5.5)
